arctrl/__init__.py
arctrl/arc.py
arctrl/arctrl.py
arctrl/column_index.py
arctrl/Contract/__init__.py
arctrl/Contract/arc.py
arctrl/Contract/arc_assay.py
arctrl/Contract/arc_investigation.py
arctrl/Contract/arc_study.py
arctrl/Contract/contract.py
arctrl/Contract/datamap.py
arctrl/Contract/git.py
arctrl/Contract/validation_packages_config.py
arctrl/ContractIO/__init__.py
arctrl/ContractIO/contract_io.py
arctrl/ContractIO/file_system_helper.py
arctrl/conversion.py
arctrl/Core/__init__.py
arctrl/Core/arc_types.py
arctrl/Core/comment.py
arctrl/Core/comment_list.py
arctrl/Core/conversion.py
arctrl/Core/data.py
arctrl/Core/data_context.py
arctrl/Core/data_file.py
arctrl/Core/data_map.py
arctrl/Core/Helper/__init__.py
arctrl/Core/Helper/collections_.py
arctrl/Core/Helper/date_time.py
arctrl/Core/Helper/hash_codes.py
arctrl/Core/Helper/identifier.py
arctrl/Core/Helper/orcid.py
arctrl/Core/Helper/printer.py
arctrl/Core/Helper/regex.py
arctrl/Core/Helper/sem_ver.py
arctrl/Core/Helper/url.py
arctrl/Core/identifier_setters.py
arctrl/Core/iproperty_value.py
arctrl/Core/ontology_annotation.py
arctrl/Core/ontology_source_reference.py
arctrl/Core/person.py
arctrl/Core/Process/__init__.py
arctrl/Core/Process/column_index.py
arctrl/Core/Process/component.py
arctrl/Core/Process/factor.py
arctrl/Core/Process/factor_value.py
arctrl/Core/Process/material.py
arctrl/Core/Process/material_attribute.py
arctrl/Core/Process/material_attribute_value.py
arctrl/Core/Process/material_type.py
arctrl/Core/Process/process.py
arctrl/Core/Process/process_input.py
arctrl/Core/Process/process_output.py
arctrl/Core/Process/process_parameter_value.py
arctrl/Core/Process/process_sequence.py
arctrl/Core/Process/protocol.py
arctrl/Core/Process/protocol_parameter.py
arctrl/Core/Process/sample.py
arctrl/Core/Process/source.py
arctrl/Core/publication.py
arctrl/Core/Table/__init__.py
arctrl/Core/Table/arc_table.py
arctrl/Core/Table/arc_table_aux.py
arctrl/Core/Table/arc_tables.py
arctrl-2.5.1.dist-info/METADATA
arctrl-2.5.1.dist-info/WHEEL
arctrl-2.5.1.dist-info/RECORD
