Metadata-Version: 2.1
Name: ARCtrl
Version: 2.5.1
Summary: Library for management of Annotated Research Contexts (ARCs) using an in-memory representation and runtimer agnostic contract systems.
Home-page: https://github.com/nfdi4plants/ARCtrl
Keywords: arc,annotated research context,isa,research data,multi platform
Author: Heinrich Lukas Weil
Author-email: weil@rptu.de
Maintainer: Florian Wetzels
Requires-Python: >=3.10,<4.0
Classifier: Programming Language :: Python :: 3
Classifier: Programming Language :: Python :: 3.10
Classifier: Programming Language :: Python :: 3.11
Classifier: Programming Language :: Python :: 3.12
Classifier: Programming Language :: Python :: 3.13
Requires-Dist: openpyxl (>=3.1.5,<4.0.0)
Requires-Dist: requests (>=2.28.1,<3.0.0)
Project-URL: Repository, https://github.com/nfdi4plants/ARCtrl
